{
  "title": "UK Safety Signage Updates 2025: What You Need to Know",
  "description": "Key changes to UK workplace signage requirements and HSE guidance coming in 2025.",
  "publishedAt": "2025-01-20T00:00:00.000Z",
  "author": "Michael Torres",
  "image": "/images/blog/uk-signage-2025-updates.png",
  "category": "Compliance Updates",
  "tags": [
    "HSE",
    "Compliance",
    "2025 Updates",
    "UK Regulations",
    "BS EN ISO 7010"
  ],
  "featured": true,
  "draft": false,
  "body": {
    "raw": "\n# UK Safety Signage Updates 2025: What You Need to Know\n\nThe Health and Safety Executive (HSE) has published updated guidance on workplace signage requirements that affect UK businesses in 2025.\n\n## Key Changes\n\n### 1. Enhanced Hazard Communication\n\nUpdated guidance recommends more specific hazard symbols for chemical storage areas, aligned with BS EN ISO 7010 pictograms.\n\n### 2. Photoluminescent Requirements\n\nEmergency exit signs in buildings with more than 50 occupants should now include photoluminescent elements to ensure visibility during power outages.\n\n### 3. Digital Signage Considerations\n\nNew HSE guidance addresses the use of digital safety displays in modern workplaces, ensuring they meet the requirements of the Health and Safety (Safety Signs and Signals) Regulations 1996.\n\n## Timeline\n\n- **Q1 2025**: Updated HSE guidance published\n- **Q2 2025**: Recommended review period for businesses\n- **Q4 2025**: Full adoption recommended\n\n## How to Prepare\n\n1. Audit your current signage against BS EN ISO 7010\n2. Identify gaps in compliance with UK regulations\n3. Order replacement signs early\n4. Train your team on any new requirements\n\nStay ahead of the curve by reviewing your signage now to ensure compliance with UK workplace safety regulations.\n",
    "html": "<h1>UK Safety Signage Updates 2025: What You Need to Know</h1>\n<p>The Health and Safety Executive (HSE) has published updated guidance on workplace signage requirements that affect UK businesses in 2025.</p>\n<h2>Key Changes</h2>\n<h3>1. Enhanced Hazard Communication</h3>\n<p>Updated guidance recommends more specific hazard symbols for chemical storage areas, aligned with BS EN ISO 7010 pictograms.</p>\n<h3>2. Photoluminescent Requirements</h3>\n<p>Emergency exit signs in buildings with more than 50 occupants should now include photoluminescent elements to ensure visibility during power outages.</p>\n<h3>3. Digital Signage Considerations</h3>\n<p>New HSE guidance addresses the use of digital safety displays in modern workplaces, ensuring they meet the requirements of the Health and Safety (Safety Signs and Signals) Regulations 1996.</p>\n<h2>Timeline</h2>\n<ul>\n<li><strong>Q1 2025</strong>: Updated HSE guidance published</li>\n<li><strong>Q2 2025</strong>: Recommended review period for businesses</li>\n<li><strong>Q4 2025</strong>: Full adoption recommended</li>\n</ul>\n<h2>How to Prepare</h2>\n<ol>\n<li>Audit your current signage against BS EN ISO 7010</li>\n<li>Identify gaps in compliance with UK regulations</li>\n<li>Order replacement signs early</li>\n<li>Train your team on any new requirements</li>\n</ol>\n<p>Stay ahead of the curve by reviewing your signage now to ensure compliance with UK workplace safety regulations.</p>"
  },
  "_id": "blog/osha-2025-updates.md",
  "_raw": {
    "sourceFilePath": "blog/osha-2025-updates.md",
    "sourceFileName": "osha-2025-updates.md",
    "sourceFileDir": "blog",
    "contentType": "markdown",
    "flattenedPath": "blog/osha-2025-updates"
  },
  "type": "BlogPost",
  "slug": "osha-2025-updates",
  "url": "/blog/osha-2025-updates"
}